wads_test/__init__.py
wads_test-0.0.2.dist-info/METADATA
wads_test-0.0.2.dist-info/WHEEL
wads_test-0.0.2.dist-info/licenses/LICENSE
wads_test-0.0.2.dist-info/RECORD
