Metadata-Version: 2.4
Name: wads_test
Version: 0.0.2
Summary: A repo to test wads repo management functionality
Project-URL: Homepage, https://github.com/i2mint/wads_test
Project-URL: Repository, https://github.com/i2mint/wads_test
Project-URL: Documentation, https://i2mint.github.io/wads_test
License: mit
License-File: LICENSE
Requires-Python: >=3.10
Provides-Extra: dev
Requires-Dist: pytest-cov>=4.0; extra == 'dev'
Requires-Dist: pytest>=7.0; extra == 'dev'
Requires-Dist: ruff>=0.1.0; extra == 'dev'
Provides-Extra: docs
Requires-Dist: sphinx-rtd-theme>=1.0; extra == 'docs'
Requires-Dist: sphinx>=6.0; extra == 'docs'
